motils.py
motils-0.1.1.dist-info/DESCRIPTION.rst
motils-0.1.1.dist-info/METADATA
motils-0.1.1.dist-info/RECORD
motils-0.1.1.dist-info/WHEEL
motils-0.1.1.dist-info/metadata.json
motils-0.1.1.dist-info/top_level.txt
